{
  "posts": {
    "2": {
      "original": {
        "title": "[Node.js] 트랜잭션을 활용한 테스트 격리 환경 구현하기 (1/2) | 솔루션 찾기",
        "url": "https://ko.puleugo.dev/201",
        "language": "ko-KR",
        "uploadedAt": "2024-07-31"
      },
      "translatedLanguages": [
        "en"
      ],
      "translated": {
        "en": [
          {
            "title": "[Node.js] Implementing a Test Isolation Environment Using Transactions (1/2) | Finding Solutions",
            "url": "https://medium.com/@puleugo/node-js-implementing-a-test-isolation-environment-using-transactions-1-2-finding-solutions-0095561fd4e4"
          }
        ]
      }
    },
    "3": {
      "original": {
        "title": "만개의 테스트를 작성하지 마라.",
        "url": "https://ko.puleugo.dev/202",
        "language": "ko-KR",
        "uploadedAt": "2024-08-10"
      },
      "translatedLanguages": [
        "en"
      ],
      "translated": {
        "en": [
          {
            "title": "Don't Write Ten Thousand Tests",
            "url": "https://medium.com/@puleugo/dont-write-ten-thousand-tests-e0df2a40517a"
          }
        ]
      }
    },
    "4": {
      "original": {
        "title": "티스토리에 마진 넣는법",
        "url": "https://ko.puleugo.dev/203",
        "language": "ko-KR",
        "uploadedAt": "2024-08-11"
      },
      "translatedLanguages": [
        "en"
      ],
      "translated": {
        "en": [
          {
            "title": "How to Add Margin in Tistory",
            "url": "https://medium.com/@puleugo/how-to-add-margin-in-tistory-25704c2f63f0"
          }
        ]
      }
    },
    "5": {
      "original": {
        "title": "[번역] 방금 당신이 작성한 코드는 도메인 로직인가? | What is domain logic?",
        "url": "https://ko.puleugo.dev/204",
        "language": "ko-KR",
        "uploadedAt": "2024-08-12"
      },
      "translatedLanguages": [
        "en"
      ],
      "translated": {
        "en": [
          {
            "title": "Is the Code You Just Wrote Domain Logic?",
            "url": "https://medium.com/@puleugo/is-the-code-you-just-wrote-domain-logic-a1e7ac1b7dc3"
          }
        ]
      }
    },
    "6": {
      "original": {
        "title": "개발자의 이상적인 해커톤 준비 방법",
        "url": "https://ko.puleugo.dev/205",
        "language": "ko-KR",
        "uploadedAt": "2024-08-19"
      },
      "translatedLanguages": [
        "en"
      ],
      "translated": {
        "en": [
          {
            "title": "How to Prepare for a Hackathon as a Developer",
            "url": "https://medium.com/@puleugo/how-to-prepare-for-a-hackathon-as-a-developer-bf596d1becc9"
          }
        ]
      }
    },
    "7": {
      "original": {
        "title": "당신의 블로그, 계왕권을 쓸 수 있다.",
        "url": "https://ko.puleugo.dev/206",
        "language": "ko-KR",
        "uploadedAt": "2024-08-19"
      },
      "translatedLanguages": [
        "en"
      ],
      "translated": {
        "en": [
          {
            "title": "Your Blog Can Use Kaio-Ken",
            "url": "https://medium.com/@puleugo/your-blog-can-use-kaio-ken-fb6c4d6a15d7"
          }
        ]
      }
    },
    "8": {
      "original": {
        "title": "KAIST GDSC 해커톤 참여, 발표 회고",
        "url": "https://ko.puleugo.dev/207",
        "language": "ko-KR",
        "uploadedAt": "2024-08-26"
      },
      "translatedLanguages": [
        "en"
      ],
      "translated": {
        "en": [
          {
            "title": "Reflections on Participating in and Presenting at the KAIST GDSC Hackathon",
            "url": "https://medium.com/@puleugo/reflections-on-participating-in-and-presenting-at-the-kaist-gdsc-hackathon-cfaddf8f47a5"
          }
        ]
      }
    },
    "9": {
      "original": {
        "title": "[리뷰] 자바스크립트 + 리액트 디자인 패턴",
        "url": "https://ko.puleugo.dev/208",
        "language": "ko-KR",
        "uploadedAt": "2024-08-29"
      },
      "translatedLanguages": [
        "en"
      ],
      "translated": {
        "en": [
          {
            "title": "[Review] JavaScript + React Design Patterns",
            "url": "https://medium.com/@puleugo/review-javascript-react-design-patterns-67b64e366748"
          }
        ]
      }
    },
    "10": {
      "original": {
        "title": "괴물 메서드 리팩터링과 성능개선하기 | 안전하게 리팩터링하기",
        "url": "https://ko.puleugo.dev/209",
        "language": "ko-KR",
        "uploadedAt": "2024-09-16"
      },
      "translatedLanguages": [
        "en"
      ],
      "translated": {
        "en": [
          {
            "title": "Refactoring Monster Methods and Improving Performance | Refactor Safely",
            "url": "https://medium.com/@puleugo/refactoring-monster-methods-and-improving-performance-refactor-safely-0fe2f2140d22"
          }
        ]
      }
    },
    "11": {
      "original": {
        "title": "[계왕권 프로젝트] 베타버전 개발기",
        "url": "https://ko.puleugo.dev/210",
        "language": "ko-KR",
        "uploadedAt": "2024-11-11"
      },
      "translatedLanguages": [
        "en"
      ],
      "translated": {
        "en": [
          {
            "title": "[King Kai Fist Project] Beta Version Development Story",
            "url": "https://medium.com/@puleugo/king-kai-fist-project-beta-version-development-story-032cb30c3aea"
          }
        ]
      }
    },
    "19": {
      "original": {
        "title": "[계왕권 출시] 당신의 블로그 가치를 44배 향상시켜주는 서비스",
        "url": "https://ko.puleugo.dev/211",
        "language": "ko-KR",
        "uploadedAt": "2024-11-12"
      },
      "translatedLanguages": [
        "en"
      ],
      "translated": {
        "en": [
          {
            "title": "[Kaio-Ken Launch] A Service That Boosts Your Blog's Value by 44 Times",
            "url": "https://medium.com/@puleugo/kaio-ken-launch-a-service-that-boosts-your-blogs-value-by-44-times-eb16ac434b13"
          }
        ]
      }
    },
    "20": {
      "original": {
        "title": "가장 후회하는 블로그 커스터마이징",
        "url": "https://ko.puleugo.dev/212",
        "language": "ko-KR",
        "uploadedAt": "2024-11-13"
      },
      "translatedLanguages": [
        "en"
      ],
      "translated": {
        "en": [
          {
            "title": "The Most Regrettable Blog Customization",
            "url": "https://medium.com/@puleugo/the-most-regrettable-blog-customization-992442654f4b"
          }
        ]
      }
    },
    "21": {
      "original": {
        "title": "이미지 로드 속도 향상하기",
        "url": "https://ko.puleugo.dev/213",
        "language": "ko-KR",
        "uploadedAt": "2024-11-17"
      },
      "translatedLanguages": [
        "en"
      ],
      "translated": {
        "en": [
          {
            "title": "Enhancing Image Load Speed",
            "url": "https://medium.com/@puleugo/enhancing-image-load-speed-c657cb815b85"
          }
        ]
      }
    },
    "31": {
      "original": {
        "title": "상호 존중하는 PR 만들기",
        "url": "https://ko.puleugo.dev/214",
        "language": "ko-KR",
        "uploadedAt": "2024-11-24"
      },
      "translatedLanguages": [
        "en"
      ],
      "translated": {
        "en": [
          {
            "title": "Creating a Mutually Respectful PR",
            "url": "https://medium.com/@puleugo/creating-a-mutually-respectful-pr-7c8f3de829c6"
          }
        ]
      }
    },
    "41": {
      "original": {
        "title": "Redis는 항상 옳은가? (Redis vs Another Plan)",
        "url": "https://ko.puleugo.dev/215",
        "language": "ko-KR",
        "uploadedAt": "2024-12-29"
      },
      "translatedLanguages": [
        "en"
      ],
      "translated": {
        "en": [
          {
            "title": "Is Redis Always the Right Choice? (Redis vs Another Plan)",
            "url": "https://medium.com/@puleugo/is-redis-always-the-right-choice-redis-vs-another-plan-91045182dd78"
          }
        ]
      }
    },
    "51": {
      "original": {
        "title": "[NestJS] AdminJS 프로덕션 배포하기",
        "url": "https://ko.puleugo.dev/216",
        "language": "ko-KR",
        "uploadedAt": "2025-02-16"
      },
      "translatedLanguages": [
        "en"
      ],
      "translated": {
        "en": [
          {
            "title": "Deploying AdminJS to Production in NestJS",
            "url": "https://medium.com/@puleugo/deploying-adminjs-to-production-in-nestjs-79dfccbf3d3e"
          }
        ]
      }
    },
    "61": {
      "original": {
        "title": "[AdminJS 에러] Cannot find module '@tiptap/pm/state'",
        "url": "https://ko.puleugo.dev/217",
        "language": "ko-KR",
        "uploadedAt": "2025-03-03"
      },
      "translatedLanguages": [
        "en"
      ],
      "translated": {
        "en": [
          {
            "title": "[AdminJS Error] Cannot find module '@tiptap/pm/state'",
            "url": "https://medium.com/@puleugo/adminjs-error-cannot-find-module-tiptap-pm-state-991d8b2be580"
          }
        ]
      }
    }
  },
  "blogs": [
    {
      "title": "푸르고의 개발 블로그",
      "platform": "Tistory",
      "language": "ko-KR",
      "rssUrl": "https://ko.puleugo.dev/rss",
      "lastPublishedIndex": 61,
      "lastPublishedAt": "2025-04-20",
      "type": "PUBLISHER"
    },
    {
      "title": "푸르고의 개발 블로그",
      "platform": "Medium",
      "language": "en",
      "rssUrl": "https://-.or.kr/",
      "lastPublishedIndex": 61,
      "lastPublishedAt": "2025-03-04",
      "type": "SUBSCRIBER"
    }
  ],
  "lastExecutedAt": "2025-04-20"
}